image_processing/__init__.py
image_processing/processing/__init__.py
image_processing/processing/combination.py
image_processing/processing/transformation.py
image_processing/utils/__init__.py
image_processing/utils/io.py
image_processing/utils/plot.py
package_image_template_processing_2-0.0.2.dist-info/METADATA
package_image_template_processing_2-0.0.2.dist-info/WHEEL
package_image_template_processing_2-0.0.2.dist-info/top_level.txt
package_image_template_processing_2-0.0.2.dist-info/RECORD
