Metadata-Version: 2.1
Name: package-image-template-processing-2
Version: 0.0.2
Summary: Template packages
Home-page: https://github.com/lucimarNeves/package-template-image_dio
Author: LucimarN
Author-email: lucimar.neves@gmail.com
Requires-Python: >=3.8
Requires-Dist: numpy
Requires-Dist: scikit-image (>=0.16.1)
Requires-Dist: matplotlib
